snappi_ixload/Test-client-stats.py
snappi_ixload/Test-client-stats_real.py
snappi_ixload/Test_L27.py
snappi_ixload/Test_ixload_connect.py
snappi_ixload/Test_l47-loop.py
snappi_ixload/Test_l47.py
snappi_ixload/Test_l47_cps.py
snappi_ixload/Test_l47_cps_pl.py
snappi_ixload/__init__.py
snappi_ixload/common.py
snappi_ixload/demo.py
snappi_ixload/ethernet.py
snappi_ixload/exceptions.py
snappi_ixload/http_config.py
snappi_ixload/http_server_config.py
snappi_ixload/interface.py
snappi_ixload/ipv4.py
snappi_ixload/ixloadapi.py
snappi_ixload/ixrestutils.py
snappi_ixload/l47server.py
snappi_ixload/logger.py
snappi_ixload/network.py
snappi_ixload/ports.py
snappi_ixload/protocols.py
snappi_ixload/scenarios.py
snappi_ixload/snappi_api.py
snappi_ixload/stats.py
snappi_ixload/tcp.py
snappi_ixload/tcp_endpoint.py
snappi_ixload/test-bg.py
snappi_ixload/test_IxNetwork.py
snappi_ixload/test_msdtls.py
snappi_ixload/timeline_objective.py
snappi_ixload/timer.py
snappi_ixload/traffic_map.py
snappi_ixload/utils.py
snappi_ixload/validation.py
snappi_ixload-0.0.8.dist-info/METADATA
snappi_ixload-0.0.8.dist-info/WHEEL
snappi_ixload-0.0.8.dist-info/top_level.txt
snappi_ixload-0.0.8.dist-info/RECORD
