Metadata-Version: 2.4
Name: snappi_ixload
Version: 0.0.8
Summary: The Snappi Ixload Open Traffic Generator Python Package
Home-page: https://github.com/open-traffic-generator/snappi-ixload
Author: waseembaig
Author-email: waseem.baig@keysight.com
License: MIT
Keywords: snappi ixload testing open traffic generator automation
Classifier: Development Status :: 3 - Alpha
Classifier: Intended Audience :: Developers
Classifier: Topic :: Software Development :: Testing :: Traffic Generation
Classifier: License :: OSI Approved :: MIT License
Classifier: Programming Language :: Python :: 2.7
Classifier: Programming Language :: Python :: 3
Requires-Python: >=2.7, <4
Requires-Dist: requests
Provides-Extra: testing
Requires-Dist: pytest; extra == "testing"
Requires-Dist: mock; extra == "testing"
Requires-Dist: dpkt==1.9.4; extra == "testing"
Dynamic: author
Dynamic: author-email
Dynamic: classifier
Dynamic: description
Dynamic: description-content-type
Dynamic: home-page
Dynamic: keywords
Dynamic: license
Dynamic: provides-extra
Dynamic: requires-dist
Dynamic: requires-python
Dynamic: summary
